{"cameraMode":{"drawMode":0,"name":"Shaded","section":"Shading Mode"},"sceneLighting":true,"audioPlay":false,"sceneViewState":{"m_AlwaysRefresh":false,"showFog":true,"showSkybox":true,"showFlares":true,"showImageEffects":true,"showParticleSystems":true,"showVisualEffectGraphs":true,"m_FxEnabled":true},"in2DMode":false,"pivot":{"x":-6.343453407287598,"y":2.8669233322143556,"z":-8.445359230041504},"rotation":{"x":-0.14861361682415009,"y":-0.31711310148239138,"z":0.051023218780756,"w":-0.9353340268135071},"size":1.6595207452774048,"orthographic":false}