{"cameraMode":{"drawMode":0,"name":"Shaded","section":"Shading Mode"},"sceneLighting":true,"audioPlay":false,"sceneViewState":{"m_AlwaysRefresh":false,"showFog":true,"showSkybox":true,"showFlares":true,"showImageEffects":true,"showParticleSystems":true,"showVisualEffectGraphs":true,"m_FxEnabled":true},"in2DMode":false,"pivot":{"x":22.770856857299806,"y":-9.93742561340332,"z":2540.11181640625},"rotation":{"x":0.0699504092335701,"y":-0.12566624581813813,"z":0.008602961897850037,"w":0.9896206855773926},"size":1480.3778076171875,"orthographic":false}